psychopy_labeotech/__init__.py
psychopy_labeotech/peristalticPump/__init__.py
psychopy_labeotech/peristalticPump/classic/eau.png
psychopy_labeotech/peristalticPump/classic/reward.png
psychopy_labeotech/peristalticPump/classic/reward@2x.png
psychopy_labeotech/peristalticPump/dark/eau.png
psychopy_labeotech/peristalticPump/dark/reward.png
psychopy_labeotech/peristalticPump/dark/reward@2x.png
psychopy_labeotech/peristalticPump/light/eau.png
psychopy_labeotech/peristalticPump/light/reward.png
psychopy_labeotech/peristalticPump/light/reward@2x.png
psychopy_labeotech-0.0.1.post2.dist-info/LICENSE
psychopy_labeotech-0.0.1.post2.dist-info/METADATA
psychopy_labeotech-0.0.1.post2.dist-info/WHEEL
psychopy_labeotech-0.0.1.post2.dist-info/entry_points.txt
psychopy_labeotech-0.0.1.post2.dist-info/top_level.txt
psychopy_labeotech-0.0.1.post2.dist-info/RECORD
